{
  "simple key": {
    "message": "Clip"
  },
  "clement": {
    "message": "verkleidet und verschwunden"
  },
  "another one": {
    "message": "wurde später hinzugefügt und ist perfekt"
  },
  "some+new+entry": {
    "message": "nur dieses Mal"
  },
  "another+entry": {
    "message": "Einen anderen Eintrag testen"
  },
  "after backup creation": {
    "message": "nach Erstellung der Sicherung"
  },
  "sleek": {
    "message": "nach Erstellung der Sicherung"
  },
  "demo_key": {
    "message": "Hallo Welt"
  },
  "link1": {
    "message": "Link"
  },
  "link2": {
    "message": "Link"
  },
  "link3": {
    "message": "Link"
  },
  "simmer": {
    "message": "probieren Sie es noch einmal aus"
  },
  "changes": {
    "message": "mit beiden Händen umarmen"
  },
  "arrival": {
    "message": "hier abhängen"
  },
  "Table 2681651900 - Field 883711285 - Property 2879900210": {
    "message": "Eingabe-Nr."
  },
  "Table 2681651900 - Field 3948098573 - Property 2879900210": {
    "message": "Anzahl der Erinnerungen"
  },
  "Table 2681651900 - Field 3710982960 - Property 2879900210": {
    "message": "Buchungsdatum"
  },
  "Table 2681651900 - Field 580412389 - Property 2879900210": {
    "message": "Datum des Dokuments"
  },
  "Table 2681651900 - Field 4085727052 - Property 2879900210": {
    "message": "Fälligkeitsdatum"
  },
  "Table 2681651900 - Field 2363328873 - Property 2879900210": {
    "message": "Dokumenttyp"
  },
  "Table 2681651900 - Field 486908828 - Property 2879900210": {
    "message": "Dokumenten-Nr."
  },
  "Table 2681651900 - Field 3461834954 - Property 2879900210": {
    "message": "Beschreibung"
  },
  "Table 2681651900 - Field 1077555671 - Property 2879900210": {
    "message": "Ursprünglicher Betrag"
  },
  "Table 2681651900 - Field 2975378708 - Property 2879900210": {
    "message": "Verbleibender Betrag"
  },
  "Table 2681651900 - Field 4200184881 - Property 2879900210": {
    "message": "Nein."
  },
  "Table 2681651900 - Field 636392376 - Property 2879900210": {
    "message": "Betrag"
  },
  "Table 2681651900 - Field 1213267064 - Property 2879900210": {
    "message": "Zinssatz"
  },
  "Table 2681651900 - Field 2139693550 - Property 2879900210": {
    "message": "Gen. Prod. Buchungsgruppe"
  },
  "Table 2681651900 - Field 1246077090 - Property 2879900210": {
    "message": "MwSt. %"
  },
  "Table 2681651900 - Field 2971014054 - Property 2879900210": {
    "message": "Art der Mehrwertsteuerberechnung"
  },
  "Table 2681651900 - Field 1108276017 - Property 2879900210": {
    "message": "MwSt.-Betrag"
  },
  "Table 2681651900 - Field 2552458873 - Property 2879900210": {
    "message": "Steuergruppen-Code"
  },
  "Table 2681651900 - Field 236064653 - Property 2879900210": {
    "message": "MwSt.-Prod. Buchungsgruppe"
  },
  "Table 2681651900 - Field 2534656220 - Property 2879900210": {
    "message": "MwSt.-Kennung"
  },
  "Table 2681651900 - Field 158172202 - Property 2879900210": {
    "message": "Linientyp"
  },
  "Table 2681651900 - Field 158172202 - Property 62802879": {
    "message": "Erinnerungszeile,Nicht fällig,Anfangstext,Endtext,Runde,In Warteschleife,Zusätzliche Gebühr,Zeilengebühr"
  },
  "Table 2681651900 - Field 2162283589 - Property 2879900210": {
    "message": "Code der Mehrwertsteuerklausel"
  },
  "Table 2681651900 - Field 400684573 - Property 2879900210": {
    "message": "Gilt für Dokumenttyp"
  },
  "Table 2681651900 - Field 677070472 - Property 2879900210": {
    "message": "Gilt für Dokument-Nr."
  },
  "Table 2681651900 - Field 1746606869 - Property 2879900210": {
    "message": "Detaillierter Zinssatzeintrag"
  },
  "Table 2681651900 - Field 2283884360 - Property 2879900210": {
    "message": "Vom System erstellter Eintrag"
  },
  "Table 2681651900 - NamedType 4094643921": {
    "message": "%1 auf %2 und %3 müssen identisch sein."
  },
  "Table 2681651900 - NamedType 1984498423": {
    "message": "%1 muss %2 oder %3 sein."
  },
  "Table 2681651900 - NamedType 3593856238": {
    "message": "%1 mit %2 %3 ist nicht geöffnet."
  },
  "Table 2681651900 - NamedType 3459220650": {
    "message": "%1 %2 in %3 ist nicht überfällig."
  },
  "Table 2681651900 - NamedType 659963034": {
    "message": "Die Zeilengebühr für %1 %2 auf Erinnerungsebene %3 wurde bereits ausgestellt."
  },
  "Table 2681651900 - NamedType 885110970": {
    "message": "%1 muss positiv sein."
  },
  "Table 2681651900 - NamedType 2618258002": {
    "message": "Es ist nicht genug Platz, um Zeilen mit zusätzlichen Zinssätzen einzufügen."
  },
  "Table 2681651900 - NamedType 2800588376": {
    "message": "Zinssatz mit Startdatum vor %1 erstellen."
  },
  "Table 3280694829 - Property 2879900210": {
    "message": "Erinnerungsbedingungen"
  },
  "Table 3280694829 - Field 3004954119 - Property 2879900210": {
    "message": "Code"
  },
  "Table 3280694829 - Field 3461834954 - Property 2879900210": {
    "message": "Beschreibung"
  },
  "Table 3280694829 - Field 2757499274 - Property 2879900210": {
    "message": "Zinsen veröffentlichen"
  },
  "Table 3280694829 - Field 3274756825 - Property 2879900210": {
    "message": "Zusätzliche Gebühr buchen"
  },
  "Table 3280694829 - Field 55421187 - Property 2879900210": {
    "message": "Max. Anzahl der Erinnerungen"
  },
  "Table 3280694829 - Field 650382431 - Property 2879900210": {
    "message": "Mindestbetrag (LCY)"
  },
  "Table 3280694829 - Field 3410685676 - Property 2879900210": {
    "message": "Nach dem Hinzufügen. Gebühr pro Zeile"
  },
  "Table 3280694829 - Field 2009106446 - Property 2879900210": {
    "message": "Hinweis zur Zeilengebühr im Bericht"
  },
  "Page 3280694829 - Property 2879900210": {
    "message": "Erinnerungsbedingungen"
  },
  "Page 3280694829 - Control 3004954119 - Property 1295455071": {
    "message": "Gibt einen Code an, um diesen Satz von Erinnerungsbegriffen zu identifizieren."
  },
  "Page 3280694829 - Control 3461834954 - Property 1295455071": {
    "message": "Gibt eine Beschreibung der Erinnerungsbedingungen an."
  },
  "Page 3280694829 - Control 55421187 - Property 1295455071": {
    "message": "Gibt die maximale Anzahl an Erinnerungen an, die für eine Rechnung erstellt werden können."
  },
  "Page 3280694829 - Control 2757499274 - Property 1295455071": {
    "message": "Gibt an, ob in der Erinnerung aufgeführte Zinsen auf das Hauptbuch und die Kundenkonten gebucht werden sollen."
  },
  "Page 3280694829 - Control 3274756825 - Property 1295455071": {
    "message": "Gibt an, ob eine zusätzliche Gebühr, die in der Erinnerung aufgeführt ist, auf das Hauptbuch und die Kundenkonten gebucht werden soll."
  },
  "Page 3280694829 - Control 3410685676 - Property 1295455071": {
    "message": "Gibt an, ob zusätzliche Gebühren, die in der Finanzkostenmitteilung aufgeführt sind, bei der Ausstellung der Mitteilung auf das Hauptbuch und die Kundenkonten gebucht werden sollen."
  },
  "Page 3280694829 - Control 650382431 - Property 1295455071": {
    "message": "Gibt den Mindestbetrag an, für den eine Erinnerung erstellt wird."
  },
  "Page 3280694829 - Control 2009106446 - Property 1295455071": {
    "message": "Gibt an, dass der Erinnerung Notizen zu Zeilengebühren hinzugefügt werden."
  },
  "Page 3280694829 - Action 2050659749 - Property 2879900210": {
    "message": "&Ebenen"
  },
  "Page 3280694829 - Action 2050659749 - Property 1295455071": {
    "message": "Zeigen Sie die Erinnerungsstufen an, die verwendet werden, um festzulegen, wann Erinnerungen erstellt werden können und welche Gebühren und Texte sie enthalten müssen."
  },
  "Page 3280694829 - Action 1358710565 - Property 2879900210": {
    "message": "Übersetzung"
  },
  "Page 3280694829 - Action 1358710565 - Property 1295455071": {
    "message": "Zeigen Sie den Erinnerungstext in allen anderen Sprachen an, die für Erinnerungen eingerichtet sind."
  },
  "Table 1909723412 - Property 2879900210": {
    "message": "Übersetzung der Erinnerungsbedingungen"
  },
  "Table 1909723412 - Field 1840439778 - Property 2879900210": {
    "message": "Code für Erinnerungsbedingungen"
  }
}
