{
  "simple key": "clip",
  "clement": "vêtu et disparu",
  "another one": "cela a été ajouté plus tard et c’est parfait",
  "some+new+entry": "cette fois-ci",
  "another+entry": "tester une autre entrée",
  "after backup creation": "après la création de la sauvegarde",
  "sleek": "après la création de la sauvegarde",
  "Page 3280694829 - Action 1358710565 - Property 1295455071": "Afficher le texte du rappel dans toutes les autres langues configurées pour les rappels.",
  "Table 1909723412 - Property 2879900210": "Traduction des termes du rappel",
  "Table 1909723412 - Field 1840439778 - Property 2879900210": "NOT FRENCH trnaslation"
}
